Workbook

Sheet How to use
A1: Upload test pack: drop each file into the POC as it is
A2: 48 files, one use case each. Nothing to edit: drag a file onto the upload box and compare what the POC shows with this workbook.
A4: 1-Prospecting (P01-P22): drop each file on the Prospecting upload box. Compare the check pane and the final list with "Prospecting rows" and "Prospecting accounts".
A5: 2-Account-Scoring (S01-S07) and 3-Signal-rules (G01-G14): these all use one prospect list, S00.
A6: Once: Account Scoring > New scoring > 1 · Prospect list > "Upload a prospect file" > drop S00_prospect_list_for_scoring_and_signals.csv. It is saved as a list.
A7: Then for each S or G file: choose that S00 list, set "Score as of" to 2026-10-20, and drop the file on box 2. Compare with "Signal rows" and "Scoring accounts".
A8: S01 is also scored on two later dates (shown in the "Score as of" column) to see signals fade.
A9: 4-Micro-segments-and-Review (N01-N04): each file holds a "Lead template" and a "Signal template" sheet. Upload it as the prospect list, then drop the same file as the signals; then send the scoring to Micro-segments & NBA and open For Review.
A10: Their per-account answer keys are in ../poc-test-sets (TS6, TS8, TS9, TS10).
A12: Always set Score as of to 2026-10-20 unless the row gives another date: signal ages are counted from that date.
A13: Mark each file Pass, Fail, Blocked or Not in scope in "Files" (and row by row if you want). For every Fail, add a row to the Gap Log and put its ID in "Gap ID".
A14: Rows marked "known gap" or "SHOULD" describe what the business would expect; the POC does something else today. They are expected to fail until fixed.
... A17: All companies, people and domains are invented.

Sheet Files
A1: ID | B1: Folder | C1: File | D1: Use case | E1: Why it matters | F1: How to run it | G1: Score as of | H1: What you should see | I1: Exact counts (from the POC rules) | J1: Status | K1: What actually happened | L1: Gap ID
A2: P01 | B2: 1-Prospecting | C2: P01_clean_list.xlsx | D2: A clean list | E2: The happy path: every row is fine, so nothing is flagged. | F2: Prospecting: drop P01_clean_list.xlsx on the upload box. | G2: n/a | H2: 15 rows read, 0 issues, 5 accounts, all 5 pass, 15 contacts in the final list. | I2: 15 rows read; 0 not loaded; 0 merged; 5 accounts, 5 pass; 15 in the final list. Issues: 0 stop, 0 flagged, 0 notes. | J2: Not run
A3: P02 | B3: 1-Prospecting | C3: P02_email_problems.xlsx | D3: Email problems | E3: Each row has one thing wrong (or nearly wrong) with the email or its verified flag. | F3: Prospecting: drop P02_email_problems.xlsx on the upload box. | G3: n/a | H3: Malformed emails and a non Y/N verified flag are flagged (D3); unverified emails are noted but not used to send. | I3: 12 rows read; 0 not loaded; 0 merged; 1 accounts, 1 pass; 10 in the final list. Issues: 0 stop, 5 flagged, 5 notes. | J3: Not run
A4: P03 | B4: 1-Prospecting | C4: P03_linkedin_and_no_contact_details.xlsx | D4: LinkedIn problems and missing contact details | E4: LinkedIn URL forms, and rows with no way to contact the person. | F4: Prospecting: drop P03_linkedin_and_no_contact_details.xlsx on the upload box. | G4: n/a | H4: Bad LinkedIn URLs and rows with neither email nor LinkedIn are flagged (D3); the others load. | I4: 8 rows read; 0 not loaded; 0 merged; 1 accounts, 1 pass; 7 in the final list. Issues: 0 stop, 3 flagged, 1 notes. | J4: Not run
A5: P04 | B5: 1-Prospecting | C5: P04_duplicates.xlsx | D5: Duplicate contacts | E5: The same person twice, written differently. Duplicates are merged into the first row. | F5: Prospecting: drop P04_duplicates.xlsx on the upload box. | G5: n/a | H5: 6 rows read, 3 merged as duplicates (D5), 3 contacts left. | I5: 6 rows read; 0 not loaded; 3 merged; 1 accounts, 1 pass; 3 in the final list. Issues: 0 stop, 3 flagged, 4 notes. | J5: Not run
A6: P05 | B6: 1-Prospecting | C6: P05_consent_and_opt_out.xlsx | D6: Consent and opt-out | E6: Every consent basis and opt-out value, and an account where everyone opted out. | F6: Prospecting: drop P05_consent_and_opt_out.xlsx on the upload box. | G6: n/a | H6: Fairway passes with 4 contactable; Glenrock Refining is excluded (no contacts left after suppression). | I6: 12 rows read; 0 not loaded; 0 merged; 2 accounts, 1 pass; 4 in the final list. Issues: 0 stop, 4 flagged, 4 notes. | J6: Not run
A7: P06 | B7: 1-Prospecting | C7: P06_region.xlsx | D7: Pilot region | E7: One company per country spelling. Only the six pilot countries pass; names are matched exactly (case does not matter). | F7: Prospecting: drop P06_region.xlsx on the upload box. | G7: n/a | H7: 11 accounts: 8 pass, 3 excluded (SG, Australia, no country). | I7: 11 rows read; 0 not loaded; 0 merged; 11 accounts, 8 pass; 8 in the final list. Issues: 0 stop, 1 flagged, 0 notes. | J7: Not run
A8: P07 | B8: 1-Prospecting | C8: P07_managed_separately_and_existing_customer.xlsx | D8: Managed separately and existing customer | E8: The two Y/N company flags with every kind of value. | F8: Prospecting: drop P07_managed_separately_and_existing_customer.xlsx on the upload box. | G8: n/a | H8: Anchor Refining excluded (managed separately); the other 7 pass; blank and invalid flags are flagged D3. | I8: 8 rows read; 0 not loaded; 0 merged; 8 accounts, 7 pass; 7 in the final list. Issues: 0 stop, 4 flagged, 0 notes. | J8: Not run
A9: P08 | B9: 1-Prospecting | C9: P08_company_size_formats.xlsx | D9: Company size formats | E9: Revenue and headcount written in different ways. One company per row. | F9: Prospecting: drop P08_company_size_formats.xlsx on the upload box. | G9: n/a | H9: All 9 load; commas, symbols and text in size columns are flagged D3 with what was read. | I9: 9 rows read; 0 not loaded; 0 merged; 9 accounts, 9 pass; 9 in the final list. Issues: 0 stop, 8 flagged, 0 notes. | J9: Not run
A10: P09 | B10: 1-Prospecting | C10: P09_account_types.xlsx | D10: Account types | E10: Each account type on the list, plus blank and one not on the list. | F10: Prospecting: drop P09_account_types.xlsx on the upload box. | G10: n/a | H10: All 8 load; "Trader" is flagged D3; blank is a note. | I10: 8 rows read; 0 not loaded; 0 merged; 8 accounts, 8 pass; 8 in the final list. Issues: 0 stop, 1 flagged, 1 notes. | J10: Not run
A11: P10 | B11: 1-Prospecting | C11: P10_industry_classification.xlsx | D11: Industry and site classification | E11: How each industry and site process maps to a vertical (core, adjacent or other). | F11: Prospecting: drop P10_industry_classification.xlsx on the upload box. | G11: n/a | H11: All 8 load; Echo Water and Halo Chemicals are held for review as Other; Flint Energy is flagged for no industry. | I11: 8 rows read; 0 not loaded; 0 merged; 8 accounts, 8 pass; 8 in the final list. Issues: 0 stop, 1 flagged, 0 notes. | J11: Not run
A12: P11 | B12: 1-Prospecting | C12: P11_job_titles_and_persona.xlsx | D12: Job titles and persona | E12: Which job titles count as the primary persona (the buyer), secondary, or none. | F12: Prospecting: drop P11_job_titles_and_persona.xlsx on the upload box. | G12: n/a | H12: All 15 load in one account; 6 primary, 6 secondary, 3 none; the blank title is flagged. | I12: 15 rows read; 0 not loaded; 0 merged; 1 accounts, 1 pass; 15 in the final list. Issues: 0 stop, 1 flagged, 0 notes. | J12: Not run
A13: P12 | B13: 1-Prospecting | C13: P12_owner_rep.xlsx | D13: Owner rep | E13: The owner_email column: who the account belongs to. | F13: Prospecting: drop P12_owner_rep.xlsx on the upload box. | G13: n/a | H13: All 6 load; blank and invalid owners are flagged D3. | I13: 6 rows read; 0 not loaded; 0 merged; 6 accounts, 6 pass; 6 in the final list. Issues: 0 stop, 3 flagged, 0 notes. | J13: Not run
... A49: N04 | B49: 4-Micro-segments-and-Review | C49: N04_rep_ownership.xlsx | D49: Rep ownership and visibility | E49: Who sees which item: the demo Sales rep role is Rep A (rep.a@client-sample.com) and the Sales manager sees everyone. Owners for Rep A, Rep B, no owner, an owner who is not a user, an owner in capitals, and an owner that is not an email. | F49: Account Scoring: "Upload a prospect file" = N04_rep_ownership.xlsx (reads its "Lead template" sheet); Score as of 2026-10-20; drop the same file on box 2 (reads "Signal template"). Then send to Micro-segments & NBA and open For Review. | G49: 2026-10-20 | H49: As in TS10 (answer key in ../poc-test-sets). | I49: Tiers: A 5, B 4. Segments: Inquiry 5, Engagement 4; 0 exception(s). | J49: Not run

Sheet Prospecting rows
A1: File | B1: Row | C1: What the row tests | D1: Expected flags (field: code issue) | E1: Expected notes | F1: Expected contact status | G1: Persona | H1: Reachable by | I1: Status | J1: What actually happened
A2: P01 | B2: 2 | C2: Primary persona, verified email and LinkedIn | D2: None | F2: In the final list | G2: Primary | H2: email and LinkedIn | I2: Not run
A3: P01 | B3: 3 | C3: Secondary persona | D3: None | F3: In the final list | G3: Secondary | H3: email and LinkedIn | I3: Not run
A4: P01 | B4: 4 | C4: No persona (still in the list) | D4: None | F4: In the final list | G4: None | H4: email and LinkedIn | I4: Not run
A5: P01 | B5: 5 | C5: Primary persona, verified email and LinkedIn | D5: None | F5: In the final list | G5: Primary | H5: email and LinkedIn | I5: Not run
A6: P01 | B6: 6 | C6: Secondary persona | D6: None | F6: In the final list | G6: Secondary | H6: email and LinkedIn | I6: Not run
A7: P01 | B7: 7 | C7: No persona (still in the list) | D7: None | F7: In the final list | G7: None | H7: email and LinkedIn | I7: Not run
A8: P01 | B8: 8 | C8: Primary persona, verified email and LinkedIn | D8: None | F8: In the final list | G8: Primary | H8: email and LinkedIn | I8: Not run
A9: P01 | B9: 9 | C9: Secondary persona | D9: None | F9: In the final list | G9: Secondary | H9: email and LinkedIn | I9: Not run
A10: P01 | B10: 10 | C10: No persona (still in the list) | D10: None | F10: In the final list | G10: None | H10: email and LinkedIn | I10: Not run
A11: P01 | B11: 11 | C11: Primary persona, verified email and LinkedIn | D11: None | F11: In the final list | G11: Primary | H11: email and LinkedIn | I11: Not run
A12: P01 | B12: 12 | C12: Secondary persona | D12: None | F12: In the final list | G12: Secondary | H12: email and LinkedIn | I12: Not run
A13: P01 | B13: 13 | C13: No persona (still in the list) | D13: None | F13: In the final list | G13: None | H13: email and LinkedIn | I13: Not run
... A20: P02 | B20: 5 | C20: Two @ signs: malformed | D20: email: D3 Email "joanne.sim@@coralbayrefining.example" is malformed | F20: In the final list | G20: Primary | H20: LinkedIn | I20: Not run
A21: P02 | B21: 6 | C21: Clean email, no LinkedIn: email only | D21: None | E21: linkedin_url: No LinkedIn URL | F21: In the final list | G21: Primary | H21: email | I21: Not run
A22: P02 | B22: 7 | C22: Email in capitals: accepted and read in lower case | D22: None | F22: In the final list | G22: Primary | H22: email and LinkedIn | I22: Not run
A23: P02 | B23: 8 | C23: Verified written TRUE instead of Y: flagged, email treated as not verified | D23: email_verified: D3 "TRUE" isn't Y or N | F23: In the final list | G23: Primary | H23: LinkedIn | I23: Not run
A24: P02 | B24: 9 | C24: Verified written "yes": accepted as Y | D24: None | F24: In the final list | G24: Primary | H24: email and LinkedIn | I24: Not run
A25: P02 | B25: 10 | C25: Not verified: loaded, email not used; reached by LinkedIn | D25: None | E25: email_verified: Email not verified | F25: In the final list | G25: Primary | H25: LinkedIn | I25: Not run
A26: P02 | B26: 11 | C26: Verified left blank: treated as not verified | D26: None | E26: email_verified: Email not verified | F26: In the final list | G26: Primary | H26: LinkedIn | I26: Not run
A27: P02 | B27: 12 | C27: Malformed email and no LinkedIn: no way to reach them | D27: email: D3 Email "omar.aziz@coralbay" is malformed | F27: In the list, not contactable (no usable email or LinkedIn) | G27: Primary | H27: none | I27: Not run
A28: P02 | B28: 13 | C28: Not verified and no LinkedIn: not contactable | D28: None | E28: email_verified: Email not verified linkedin_url: No LinkedIn URL | F28: In the list, not contactable (no usable email or LinkedIn) | G28: Primary | H28: none | I28: Not run
A29: P03 | B29: 2 | C29: Control: clean | D29: None | F29: In the final list | G29: Primary | H29: email and LinkedIn | I29: Not run
A30: P03 | B30: 3 | C30: Company page, not a person: flagged, LinkedIn not used | D30: linkedin_url: D3 LinkedIn URL "https://www.linkedin.com/company/delta-refining" isn't a profile URL | F30: In the final list | G30: Primary | H30: email | I30: Not run
A31: P03 | B31: 4 | C31: Not a LinkedIn URL: flagged | D31: linkedin_url: D3 LinkedIn URL "www.facebook.com/huimin" isn't a profile URL | F31: In the final list | G31: Primary | H31: email | I31: Not run
A32: P03 | B32: 5 | C32: No https:// or www: accepted | D32: None | F32: In the final list | G32: Primary | H32: email and LinkedIn | I32: Not run
A33: P03 | B33: 6 | C33: Trailing slash: accepted | D33: None | F33: In the final list | G33: Primary | H33: email and LinkedIn | I33: Not run
A34: P03 | B34: 7 | C34: Old /pub/ profile URL: accepted | D34: None | F34: In the final list | G34: Primary | H34: email and LinkedIn | I34: Not run
A35: P03 | B35: 8 | C35: No email, LinkedIn only: reached on LinkedIn | D35: None | E35: email: No email | F35: In the final list | G35: Primary | H35: LinkedIn | I35: Not run
A36: P03 | B36: 9 | C36: No email and no LinkedIn: flagged, kept on the account, not contactable | D36: email / linkedin_url: D3 No email and no LinkedIn URL | F36: In the list, not contactable (no usable email or LinkedIn) | G36: Primary | H36: none | I36: Not run
A37: P04 | B37: 2 | C37: First row for Grace Teh (no LinkedIn) | D37: None | E37: linkedin_url: No LinkedIn URL | F37: In the final list | G37: Primary | H37: email and LinkedIn | I37: Not run
A38: P04 | B38: 3 | C38: Same email in capitals: merged into the row above; its LinkedIn fills the blank | D38: email: D5 Duplicate of row 2 (Grace Teh) | F38: Merged into an earlier row | I38: Not run
A39: P04 | B39: 4 | C39: First row for Ivan Lo | D39: None | F39: In the final list | G39: Primary | H39: email and LinkedIn | I39: Not run
A40: P04 | B40: 5 | C40: Same LinkedIn profile, different URL form, no email: merged | D40: linkedin_url: D5 Duplicate of row 4 (Ivan Lo) | E40: email: No email | F40: Merged into an earlier row | I40: Not run
A41: P04 | B41: 6 | C41: Same name, different email, no LinkedIn: a different contact, not merged | D41: None | E41: linkedin_url: No LinkedIn URL | F41: In the final list | G41: Primary | H41: email | I41: Not run
A42: P04 | B42: 7 | C42: Another company's row reusing Grace Teh's email: merged into her (worth a look) | D42: email: D5 Duplicate of row 2 (Grace Teh) | E42: linkedin_url: No LinkedIn URL | F42: Merged into an earlier row | I42: Not run
A43: P05 | B43: 2 | C43: legitimate interest: contactable | D43: None | F43: In the final list | G43: Primary | H43: email and LinkedIn | I43: Not run
A44: P05 | B44: 3 | C44: existing customer: contactable | D44: None | F44: In the final list | G44: Primary | H44: email and LinkedIn | I44: Not run
A45: P05 | B45: 4 | C45: opted in: contactable | D45: None | F45: In the final list | G45: Primary | H45: email and LinkedIn | I45: Not run
A46: P05 | B46: 5 | C46: Capitalised basis: accepted | D46: None | F46: In the final list | G46: Primary | H46: email and LinkedIn | I46: Not run
A47: P05 | B47: 6 | C47: No consent basis: flagged, not contactable | D47: consent_basis: D3 No consent basis | F47: In the list, not contactable (no consent basis) | G47: Primary | H47: email and LinkedIn | I47: Not run
A48: P05 | B48: 7 | C48: "purchased list" is not a recognised basis: flagged, not contactable | D48: consent_basis: D3 "purchased list" isn't a recognised basis | F48: In the list, not contactable (no consent basis) | G48: Primary | H48: email and LinkedIn | I48: Not run
A49: P05 | B49: 8 | C49: Opted out: suppressed, never contacted | D49: None | E49: opt_out: Opted out | F49: Not in the list: opted out | G49: Primary | H49: email and LinkedIn | I49: Not run
A50: P05 | B50: 9 | C50: Opt-out "yes": read as Y, suppressed | D50: None | E50: opt_out: Opted out | F50: Not in the list: opted out | G50: Primary | H50: email and LinkedIn | I50: Not run
A51: P05 | B51: 10 | C51: Opt-out blank: flagged, not contactable until confirmed | D51: opt_out: D3 opt_out is blank | F51: In the list, not contactable (opt-out not confirmed) | G51: Primary | H51: email and LinkedIn | I51: Not run
A52: P05 | B52: 11 | C52: Opt-out "maybe": flagged, not contactable | D52: opt_out: D3 "maybe" isn't Y or N | F52: In the list, not contactable (opt-out not confirmed) | G52: Primary | H52: email and LinkedIn | I52: Not run
A53: P05 | B53: 12 | C53: Glenrock: first of two, opted out | D53: None | E53: opt_out: Opted out | F53: Not in the list: account excluded (No contactable contacts after suppression) | G53: Primary | H53: email and LinkedIn | I53: Not run
A54: P05 | B54: 13 | C54: Glenrock: second of two, opted out, so the whole account is excluded | D54: None | E54: opt_out: Opted out | F54: Not in the list: account excluded (No contactable contacts after suppression) | G54: Primary | H54: email and LinkedIn | I54: Not run
A55: P06 | B55: 2 | C55: Singapore: passes | D55: None | F55: In the final list | G55: Primary | H55: email and LinkedIn | I55: Not run
A56: P06 | B56: 3 | C56: Malaysia: passes | D56: None | F56: In the final list | G56: Primary | H56: email and LinkedIn | I56: Not run
A57: P06 | B57: 4 | C57: Thailand: passes | D57: None | F57: In the final list | G57: Primary | H57: email and LinkedIn | I57: Not run
A58: P06 | B58: 5 | C58: Philippines: passes | D58: None | F58: In the final list | G58: Primary | H58: email and LinkedIn | I58: Not run
A59: P06 | B59: 6 | C59: Indonesia: passes | D59: None | F59: In the final list | G59: Primary | H59: email and LinkedIn | I59: Not run
A60: P06 | B60: 7 | C60: Vietnam: passes | D60: None | F60: In the final list | G60: Primary | H60: email and LinkedIn | I60: Not run
A61: P06 | B61: 8 | C61: Lower case "singapore": passes | D61: None | F61: In the final list | G61: Primary | H61: email and LinkedIn | I61: Not run
A62: P06 | B62: 9 | C62: Spaces around the name: passes | D62: None | F62: In the final list | G62: Primary | H62: email and LinkedIn | I62: Not run
A63: P06 | B63: 10 | C63: "SG": excluded as outside the region (confirm with the business whether codes should count) | D63: None | F63: Not in the list: account excluded (Outside the pilot region (SG)) | G63: Primary | H63: email and LinkedIn | I63: Not run
A64: P06 | B64: 11 | C64: Australia: excluded, outside the pilot region | D64: None | F64: Not in the list: account excluded (Outside the pilot region (Australia)) | G64: Primary | H64: email and LinkedIn | I64: Not run
A65: P06 | B65: 12 | C65: No country: flagged and excluded | D65: country: D3 Country is missing | F65: Not in the list: account excluded (Outside the pilot region (no country)) | G65: Primary | H65: email and LinkedIn | I65: Not run
A66: P07 | B66: 2 | C66: Managed separately Y: excluded | D66: None | F66: Not in the list: account excluded (Managed separately by Client) | G66: Primary | H66: email and LinkedIn | I66: Not run
... A87: P09 | B87: 6 | C87: Other: 0 points | D87: None | F87: In the final list | G87: Primary | H87: email and LinkedIn | I87: Not run
A88: P09 | B88: 7 | C88: Blank: noted, scores 0 | D88: None | E88: account_type: Account type is blank | F88: In the final list | G88: Primary | H88: email and LinkedIn | I88: Not run
A89: P09 | B89: 8 | C89: "Trader" is not on the list: flagged, treated as Other | D89: account_type: D3 "Trader" isn't on the list | F89: In the final list | G89: Primary | H89: email and LinkedIn | I89: Not run
A90: P09 | B90: 9 | C90: Lower case: accepted | D90: None | F90: In the final list | G90: Primary | H90: email and LinkedIn | I90: Not run
A91: P10 | B91: 2 | C91: Industry and site both say refining: Refining (core), high confidence | D91: None | F91: In the final list | G91: Primary | H91: email and LinkedIn | I91: Not run
A92: P10 | B92: 3 | C92: Petrochemicals, site not in the lookup: Petrochemicals (adjacent), from the industry | D92: None | F92: In the final list | G92: Primary | H92: email and LinkedIn | I92: Not run
A93: P10 | B93: 4 | C93: LNG: Gas processing (adjacent) | D93: None | F93: In the final list | G93: Primary | H93: email and LinkedIn | I93: Not run
A94: P10 | B94: 5 | C94: Gas processing (adjacent) | D94: None | F94: In the final list | G94: Primary | H94: email and LinkedIn | I94: Not run
A95: P10 | B95: 6 | C95: Not in the lookup: Other, held for a person to classify | D95: None | F95: In the final list | G95: Primary | H95: email and LinkedIn | I95: Not run
A96: P10 | B96: 7 | C96: No industry, refining site: flagged; Refining from the site | D96: industry: D3 Industry is missing | F96: In the final list | G96: Primary | H96: email and LinkedIn | I96: Not run
A97: P10 | B97: 8 | C97: Industry and site disagree: industry used, medium confidence | D97: None | F97: In the final list | G97: Primary | H97: email and LinkedIn | I97: Not run
A98: P10 | B98: 9 | C98: Specialty chemicals: Other, held for review | D98: None | F98: In the final list | G98: Primary | H98: email and LinkedIn | I98: Not run
A99: P11 | B99: 2 | C99: Primary | D99: None | F99: In the final list | G99: Primary | H99: email and LinkedIn | I99: Not run
A100: P11 | B100: 3 | C100: Primary | D100: None | F100: In the final list | G100: Primary | H100: email and LinkedIn | I100: Not run
... A127: P14 | B127: 2 | C127: Control: clean | D127: None | F127: In the final list | G127: Primary | H127: email and LinkedIn | I127: Not run
A128: P14 | B128: 3 | C128: No company name: row not loaded (stop) | D128: company_name: D3 Company name is missing | F128: Not loaded | I128: Not run
A129: P14 | B129: 4 | C129: No first name: loaded, flagged (draft greeting will need editing) | D129: first_name: D3 First name is missing | F129: In the final list | G129: Primary | H129: email and LinkedIn | I129: Not run
A130: P14 | B130: 5 | C130: No last name: loaded, flagged | D130: last_name: D3 Last name is missing | F130: In the final list | G130: Primary | H130: email and LinkedIn | I130: Not run
A131: P14 | B131: 6 | C131: No job title: flagged, persona none | D131: job_title: D3 Job title is missing | F131: In the final list | G131: None | H131: email and LinkedIn | I131: Not run
A132: P14 | B132: 7 | C132: No domain: flagged | D132: company_domain: D3 Company domain is missing | F132: In the final list | G132: Primary | H132: email and LinkedIn | I132: Not run
A133: P14 | B133: 8 | C133: Domain written as a web address: flagged | D133: company_domain: D3 Domain "https://www.uplandrefining.example" isn't in the form company.com | F133: In the final list | G133: Primary | H133: email and LinkedIn | I133: Not run
A134: P14 | B134: 9 | C134: Domain with no dot: flagged | D134: company_domain: D3 Domain "uplandrefining" isn't in the form company.com | F134: In the final list | G134: Primary | H134: email and LinkedIn | I134: Not run
A135: P15 | B135: 2 | C135: Row 1 | D135: None | F135: In the list, not contactable (no consent basis) | G135: Primary | H135: email and LinkedIn | I135: Not run
A136: P15 | B136: 3 | C136: Row 2 | D136: None | F136: In the list, not contactable (no consent basis) | G136: Secondary | H136: email and LinkedIn | I136: Not run
A137: P15 | B137: 4 | C137: Row 3 | D137: None | F137: In the list, not contactable (no consent basis) | G137: Primary | H137: email and LinkedIn | I137: Not run
A138: P16 | B138: 2 | C138: Not read | D138: None | F138: Not read | I138: Not run
A139: P16 | B139: 3 | C139: Not read | D139: None | F139: Not read | I139: Not run
A140: P17 | B140: 4 | C140: Data row 1 | D140: None | F140: In the final list | G140: Primary | H140: email and LinkedIn | I140: Not run
A141: P17 | B141: 5 | C141: Data row 2 | D141: None | F141: In the final list | G141: Secondary | H141: email and LinkedIn | I141: Not run
A142: P18 | B142: 2 | C142: Data row 1 | D142: None | F142: In the final list | G142: Primary | H142: email and LinkedIn | I142: Not run
A143: P18 | B143: 3 | C143: Data row 2 | D143: None | F143: In the final list | G143: Secondary | H143: email and LinkedIn | I143: Not run
A144: P21 | B144: 2 | C144: Clean | D144: None | F144: In the final list | G144: Primary | H144: email and LinkedIn | I144: Not run
A145: P21 | B145: 3 | C145: Clean | D145: None | F145: In the final list | G145: Secondary | H145: email and LinkedIn | I145: Not run
A146: P22 | B146: 2 | C146: Comma in the company name and the job title | D146: None | F146: In the final list | G146: Primary | H146: email and LinkedIn | I146: Not run
A147: P22 | B147: 3 | C147: Accented name and quotes in the title | D147: None | F147: In the final list | G147: Secondary | H147: email and LinkedIn | I147: Not run
A148: P22 | B148: 4 | C148: Apostrophe in the name | D148: None | F148: In the final list | G148: Primary | H148: email and LinkedIn | I148: Not run
A149: S00 | B149: 2 | C149: Fit 100: core, above-target revenue, refining site, existing customer, owner-operator, primary contact | D149: None | F149: In the final list | G149: Primary | H149: email and LinkedIn | I149: Not run
A150: S00 | B150: 3 | C150: Fit 100: core, above-target revenue, refining site, existing customer, owner-operator, primary contact | D150: None | F150: In the final list | G150: Secondary | H150: email and LinkedIn | I150: Not run
A151: S00 | B151: 4 | C151: Fit 100 | D151: None | F151: In the final list | G151: Primary | H151: email and LinkedIn | I151: Not run
... A168: S00 | B168: 21 | C168: Fit 49 (no size given): below the fit floor | D168: annual_revenue_usd / employee_count: D3 No company size | F168: In the final list | G168: Primary | H168: email and LinkedIn | I168: Not run
...

Sheet Prospecting accounts
A1: File | B1: Account | C1: Region and suppression checks | D1: Vertical | E1: Classification confidence | F1: Held for review | G1: Owner
A2: P01 | B2: Harbour Refining | C2: Passes | D2: Refining (core) | E2: high | F2: No | G2: rep.a@client-sample.com
A3: P01 | B3: Kestrel Petrochem | C3: Passes | D3: Petrochemicals (adjacent) | E3: medium | F3: No | G3: rep.a@client-sample.com
A4: P01 | B4: Selatan LNG | C4: Passes | D4: Gas processing (adjacent) | E4: high | F4: No | G4: rep.b@client-sample.com
A5: P01 | B5: Mekong Refining | C5: Passes | D5: Refining (core) | E5: high | F5: No | G5: rep.b@client-sample.com
A6: P01 | B6: Visayas Gas | C6: Passes | D6: Gas processing (adjacent) | E6: high | F6: No | G6: rep.a@client-sample.com
A7: P02 | B7: Coral Bay Refining | C7: Passes | D7: Refining (core) | E7: high | F7: No | G7: rep.a@client-sample.com
A8: P03 | B8: Delta Refining | C8: Passes | D8: Refining (core) | E8: high | F8: No | G8: rep.a@client-sample.com
A9: P04 | B9: Eastwind Refining | C9: Passes | D9: Refining (core) | E9: high | F9: No | G9: rep.a@client-sample.com
A10: P05 | B10: Fairway Refining | C10: Passes | D10: Refining (core) | E10: high | F10: No | G10: rep.a@client-sample.com
A11: P05 | B11: Glenrock Refining | C11: Excluded: No contactable contacts after suppression | D11: Refining (core) | E11: high | F11: No | G11: rep.a@client-sample.com
A12: P06 | B12: Jurong Fuels | C12: Passes | D12: Refining (core) | E12: high | F12: No | G12: rep.a@client-sample.com
... A87: S00 | B87: Tidewater Refining | C87: Excluded: Outside the pilot region (Australia) | D87: Refining (core) | E87: high | F87: No | G87: rep.a@client-sample.com

Sheet Signal rows
A1: File | B1: Score as of | C1: Row | D1: Company | E1: Type of signal | F1: What the row tests | G1: Expected status | H1: Code | I1: Reason, or who it was given to | J1: Person | K1: Age (days) | L1: Weight | M1: Status | N1: What actually happened
A2: S01 | B2: 2026-10-20 | C2: 2 | D2: Apex Refining | E2: Inquiry or RFQ | F2: Apex: fresh inquiry: tier A | G2: Qualified | H2: Y2 | I2: Named in the file | J2: Kai Ong | K2: 5 | L2: 100 | M2: Not run
A3: S01 | B3: 2026-10-20 | C3: 3 | D3: Bayfront Refining | E3: Installed system near end of support | F3: Bayfront: end of support: tier A | G3: Qualified | H3: Y1 | I3: Named in the file | J3: Mia Tan | K3: 120 | L3: 100 | M3: Not run
A4: S01 | B4: 2026-10-20 | C4: 4 | D4: Coldwater Refining | E4: Capital project | F4: Coldwater: capital project (weight 80): tier A | G4: Qualified | H4: Y4 | I4: Named in the file | J4: Oli Ng | K4: 40 | L4: 80 | M4: Not run
A5: S01 | B5: 2026-10-20 | C5: 5 | D5: Driftwood Refining | E5: Webinar attended | F5: Driftwood: webinar: tier B | G5: Qualified | H5: C1w | I5: Named in the file | J5: Quin Ong | K5: 10 | L5: 60 | M5: Not run
A6: S01 | B6: 2026-10-20 | C6: 6 | D6: Eastgate Refining | E6: Email clicked | F6: Eastgate: one email click: tier C | G6: Qualified | H6: C1x | I6: Named in the file | J6: Sam Sim | K6: 5 | L6: 30 | M6: Not run
A7: S01 | B7: 2026-10-20 | C7: 7 | D7: Moorland Refining | E7: Service contract renewal | F7: Moorland: service renewal | G7: Qualified | H7: Y1 | I7: Named in the file | J7: Wes Goh | K7: 30 | L7: 60 | M7: Not run
A8: S01 | B8: 2026-10-20 | C8: 8 | D8: Newhaven Petrochem | E8: Leadership change | F8: Newhaven: leadership change | G8: Qualified | H8: C1c | I8: Named in the file | J8: Yan Lee | K8: 10 | L8: 45 | M8: Not run
A9: S01 | B9: 2026-10-20 | C9: 9 | D9: Juniper Fuels | E9: Inquiry or RFQ | F9: Juniper (fit 50): inquiry | G9: Qualified | H9: Y2 | I9: Named in the file | J9: Cal Ho | K9: 5 | L9: 100 | M9: Not run
A10: S01 | B10: 2026-10-20 | C10: 10 | D10: Kingsbridge Fuels | E10: Inquiry or RFQ | F10: Kingsbridge (fit 49): qualified but not used, below the fit floor | G10: Not used | H10: Y2 | I10: Qualified, but the account is below the fit floor | J10: Dee Lim | K10: 5 | L10: 100 | M10: Not run
A11: S01 | B11: 2026-10-20 | C11: 11 | D11: Tidewater Refining | E11: Inquiry or RFQ | F11: Tidewater (excluded): qualified but not used | G11: Not used | H11: Y2 | I11: Qualified, but the account is excluded (Outside the pilot region (Australia)) | J11: Hu Koh | K11: 5 | L11: 100 | M11: Not run
A12: S01 | B12: 2026-12-20 | C12: 2 | D12: Apex Refining | E12: Inquiry or RFQ | F12: Apex: fresh inquiry: tier A | G12: Qualified | H12: Y2 | I12: Named in the file | J12: Kai Ong | K12: 66 | L12: 40 | M12: Not run
A13: S01 | B13: 2026-12-20 | C13: 3 | D13: Bayfront Refining | E13: Installed system near end of support | F13: Bayfront: end of support: tier A | G13: Qualified | H13: Y1 | I13: Named in the file | J13: Mia Tan | K13: 181 | L13: 100 | M13: Not run
... A15: S01 | B15: 2026-12-20 | C15: 5 | D15: Driftwood Refining | E15: Webinar attended | F15: Driftwood: webinar: tier B | G15: Qualified | H15: C1w | I15: Named in the file | J15: Quin Ong | K15: 71 | L15: 43.6 | M15: Not run
A16: S01 | B16: 2026-12-20 | C16: 6 | D16: Eastgate Refining | E16: Email clicked | F16: Eastgate: one email click: tier C | G16: Rejected | H16: D2 | I16: 66 days old; this signal type counts for 60 days | J16: Sam Sim | K16: 66 | M16: Not run
A17: S01 | B17: 2026-12-20 | C17: 7 | D17: Moorland Refining | E17: Service contract renewal | F17: Moorland: service renewal | G17: Qualified | H17: Y1 | I17: Named in the file | J17: Wes Goh | K17: 91 | L17: 59.3 | M17: Not run
A18: S01 | B18: 2026-12-20 | C18: 8 | D18: Newhaven Petrochem | E18: Leadership change | F18: Newhaven: leadership change | G18: Qualified | H18: C1c | I18: Named in the file | J18: Yan Lee | K18: 71 | L18: 24.5 | M18: Not run
A19: S01 | B19: 2026-12-20 | C19: 9 | D19: Juniper Fuels | E19: Inquiry or RFQ | F19: Juniper (fit 50): inquiry | G19: Qualified | H19: Y2 | I19: Named in the file | J19: Cal Ho | K19: 66 | L19: 40 | M19: Not run
A20: S01 | B20: 2026-12-20 | C20: 10 | D20: Kingsbridge Fuels | E20: Inquiry or RFQ | F20: Kingsbridge (fit 49): qualified but not used, below the fit floor | G20: Not used | H20: Y2 | I20: Qualified, but the account is below the fit floor | J20: Dee Lim | K20: 66 | L20: 40 | M20: Not run
A21: S01 | B21: 2026-12-20 | C21: 11 | D21: Tidewater Refining | E21: Inquiry or RFQ | F21: Tidewater (excluded): qualified but not used | G21: Not used | H21: Y2 | I21: Qualified, but the account is excluded (Outside the pilot region (Australia)) | J21: Hu Koh | K21: 66 | L21: 40 | M21: Not run
A22: S01 | B22: 2027-04-20 | C22: 2 | D22: Apex Refining | E22: Inquiry or RFQ | F22: Apex: fresh inquiry: tier A | G22: Rejected | H22: D2 | I22: 187 days old; this signal type counts for 90 days | J22: Kai Ong | K22: 187 | M22: Not run
A23: S01 | B23: 2027-04-20 | C23: 3 | D23: Bayfront Refining | E23: Installed system near end of support | F23: Bayfront: end of support: tier A | G23: Qualified | H23: Y1 | I23: Named in the file | J23: Mia Tan | K23: 302 | L23: 100 | M23: Not run
A24: S01 | B24: 2027-04-20 | C24: 4 | D24: Coldwater Refining | E24: Capital project | F24: Coldwater: capital project (weight 80): tier A | G24: Qualified | H24: Y4 | I24: Named in the file | J24: Oli Ng | K24: 222 | L24: 41.6 | M24: Not run
A25: S01 | B25: 2027-04-20 | C25: 5 | D25: Driftwood Refining | E25: Webinar attended | F25: Driftwood: webinar: tier B | G25: Rejected | H25: D2 | I25: 192 days old; this signal type counts for 180 days | J25: Quin Ong | K25: 192 | M25: Not run
A26: S01 | B26: 2027-04-20 | C26: 6 | D26: Eastgate Refining | E26: Email clicked | F26: Eastgate: one email click: tier C | G26: Rejected | H26: D2 | I26: 187 days old; this signal type counts for 60 days | J26: Sam Sim | K26: 187 | M26: Not run
A27: S01 | B27: 2027-04-20 | C27: 7 | D27: Moorland Refining | E27: Service contract renewal | F27: Moorland: service renewal | G27: Rejected | H27: D2 | I27: 212 days old; this signal type counts for 180 days | J27: Wes Goh | K27: 212 | M27: Not run
A28: S01 | B28: 2027-04-20 | C28: 8 | D28: Newhaven Petrochem | E28: Leadership change | F28: Newhaven: leadership change | G28: Rejected | H28: D2 | I28: 192 days old; this signal type counts for 120 days | J28: Yan Lee | K28: 192 | M28: Not run
A29: S01 | B29: 2027-04-20 | C29: 9 | D29: Juniper Fuels | E29: Inquiry or RFQ | F29: Juniper (fit 50): inquiry | G29: Rejected | H29: D2 | I29: 187 days old; this signal type counts for 90 days | J29: Cal Ho | K29: 187 | M29: Not run
A30: S01 | B30: 2027-04-20 | C30: 10 | D30: Kingsbridge Fuels | E30: Inquiry or RFQ | F30: Kingsbridge (fit 49): qualified but not used, below the fit floor | G30: Rejected | H30: D2 | I30: 187 days old; this signal type counts for 90 days | J30: Dee Lim | K30: 187 | M30: Not run
A31: S01 | B31: 2027-04-20 | C31: 11 | D31: Tidewater Refining | E31: Inquiry or RFQ | F31: Tidewater (excluded): qualified but not used | G31: Rejected | H31: D2 | I31: 187 days old; this signal type counts for 90 days | J31: Hu Koh | K31: 187 | M31: Not run
A32: S02 | B32: 2026-10-20 | C32: 2 | D32: Apex Refining | E32: Inquiry or RFQ | F32: Fresh inquiry, weight 100: score 50, A | G32: Qualified | H32: Y2 | I32: Named in the file | J32: Kai Ong | K32: 10 | L32: 100 | M32: Not run
A33: S02 | B33: 2026-10-20 | C33: 3 | D33: Bayfront Refining | E33: Inquiry or RFQ | F33: 48 days: weight 70, score exactly 35: A (the cut-off is "at least 35") | G33: Qualified | H33: Y2 | I33: Named in the file | J33: Mia Tan | K33: 48 | L33: 70 | M33: Not run
A34: S02 | B34: 2026-10-20 | C34: 4 | D34: Coldwater Refining | E34: Inquiry or RFQ | F34: 49 days: weight 68.3, score 34.2: B | G34: Qualified | H34: Y2 | I34: Named in the file | J34: Oli Ng | K34: 49 | L34: 68.3 | M34: Not run
A35: S02 | B35: 2026-10-20 | C35: 5 | D35: Driftwood Refining | E35: Inquiry or RFQ | F35: 66 days: weight 40, score exactly 20: B | G35: Qualified | H35: Y2 | I35: Named in the file | J35: Quin Ong | K35: 66 | L35: 40 | M35: Not run
A36: S02 | B36: 2026-10-20 | C36: 6 | D36: Eastgate Refining | E36: Inquiry or RFQ | F36: 67 days: weight 38.3, score 19.2: C | G36: Qualified | H36: Y2 | I36: Named in the file | J36: Sam Sim | K36: 67 | L36: 38.3 | M36: Not run
A37: S03 | B37: 2026-10-20 | C37: 2 | D37: Apex Refining | E37: Inquiry or RFQ | F37: Apex Refining: inquiry | G37: Qualified | H37: Y2 | I37: Named in the file | J37: Kai Ong | K37: 5 | L37: 100 | M37: Not run
A38: S03 | B38: 2026-10-20 | C38: 3 | D38: Moorland Refining | E38: Inquiry or RFQ | F38: Moorland Refining: inquiry | G38: Qualified | H38: Y2 | I38: Named in the file | J38: Wes Goh | K38: 5 | L38: 100 | M38: Not run
A39: S03 | B39: 2026-10-20 | C39: 4 | D39: Pebblebrook Refining | E39: Inquiry or RFQ | F39: Pebblebrook Refining: inquiry | G39: Qualified | H39: Y2 | I39: Named in the file | J39: Xin Chua | K39: 5 | L39: 100 | M39: Not run
A40: S03 | B40: 2026-10-20 | C40: 5 | D40: Newhaven Petrochem | E40: Inquiry or RFQ | F40: Newhaven Petrochem: inquiry | G40: Qualified | H40: Y2 | I40: Named in the file | J40: Yan Lee | K40: 5 | L40: 100 | M40: Not run
A41: S03 | B41: 2026-10-20 | C41: 6 | D41: Oakridge Water | E41: Inquiry or RFQ | F41: Oakridge Water: inquiry | G41: Qualified | H41: Y2 | I41: Named in the file | J41: Zed Teo | K41: 5 | L41: 100 | M41: Not run
A42: S03 | B42: 2026-10-20 | C42: 7 | D42: Quarry Hill Engineering | E42: Inquiry or RFQ | F42: Quarry Hill Engineering: inquiry | G42: Qualified | H42: Y2 | I42: Named in the file | J42: Abe Wee | K42: 5 | L42: 100 | M42: Not run
A43: S03 | B43: 2026-10-20 | C43: 8 | D43: Larkspur Refining | E43: Inquiry or RFQ | F43: Larkspur Refining: inquiry | G43: Qualified | H43: Y2 | I43: Named in the file | J43: Bea Ang | K43: 5 | L43: 100 | M43: Not run
... A52: S04 | B52: 2026-10-20 | C52: 8 | D52: Coldwater Refining | E52: Webinar attended | F52: Coldwater: another webinar, different date: both count | G52: Qualified | H52: C1w | I52: Named in the file | J52: Oli Ng | K52: 50 | L52: 52 | M52: Not run
A53: S05 | B53: 2026-10-20 | C53: 2 | D53: Stonegate Refining | E53: Installed system (current) | F53: Stonegate: knocked out | G53: Used for a knock-out | I53: Current pilot product installed: account excluded | M53: Not run
A54: S05 | B54: 2026-10-20 | C54: 3 | D54: Stonegate Refining | E54: Inquiry or RFQ | F54: Stonegate: inquiry is qualified but not used (account excluded) | G54: Not used | H54: Y2 | I54: Qualified, but the account is excluded (Pilot product already installed at the site) | J54: Gil Ong | K54: 5 | L54: 100 | M54: Not run
A55: S05 | B55: 2026-10-20 | C55: 4 | D55: Quarry Hill Engineering | E55: Installed system (current) | F55: Quarry Hill: knock-out naming a person not in the list: still knocks the account out | G55: Used for a knock-out | I55: Current pilot product installed: account excluded | M55: Not run
A56: S05 | B56: 2026-10-20 | C56: 5 | D56: Apex Refining | E56: Installed system near end of support | F56: Apex: "near end of support" is a buying signal, not a knock-out | G56: Qualified | H56: Y1 | I56: Named in the file | J56: Kai Ong | K56: 100 | L56: 100 | M56: Not run
A57: S07 | B57: 2026-10-20 | C57: 2 | D57: Rosewood Refining | E57: Inquiry or RFQ | F57: Rosewood, Eli (opted out): inquiry | G57: Qualified | H57: Y2 | I57: Named in the file | J57: Eli Tan | K57: 5 | L57: 100 | M57: Not run
A58: S07 | B58: 2026-10-20 | C58: 3 | D58: Apex Refining | E58: Inquiry or RFQ | F58: Apex: control | G58: Qualified | H58: Y2 | I58: Named in the file | J58: Kai Ong | K58: 5 | L58: 100 | M58: Not run
A59: G01 | B59: 2026-10-20 | C59: 2 | D59: Apex Refining | E59: Inquiry or RFQ | F59: Inquiry or RFQ: qualified | G59: Qualified | H59: Y2 | I59: Named in the file | J59: Kai Ong | K59: 3 | L59: 100 | M59: Not run
A60: G01 | B60: 2026-10-20 | C60: 3 | D60: Apex Refining | E60: Installed system near end of support | F60: Installed system near end of support: qualified | G60: Qualified | H60: Y1 | I60: Named in the file | J60: Kai Ong | K60: 4 | L60: 100 | M60: Not run
A61: G01 | B61: 2026-10-20 | C61: 4 | D61: Apex Refining | E61: Service contract renewal | F61: Service contract renewal: qualified | G61: Qualified | H61: Y1 | I61: Named in the file | J61: Kai Ong | K61: 5 | L61: 60 | M61: Not run
A62: G01 | B62: 2026-10-20 | C62: 5 | D62: Apex Refining | E62: Capital project | F62: Capital project: qualified | G62: Qualified | H62: Y4 | I62: Named in the file | J62: Kai Ong | K62: 6 | L62: 80 | M62: Not run
A63: G01 | B63: 2026-10-20 | C63: 6 | D63: Apex Refining | E63: Leadership change | F63: Leadership change: qualified | G63: Qualified | H63: C1c | I63: Named in the file | J63: Kai Ong | K63: 7 | L63: 45 | M63: Not run
A64: G01 | B64: 2026-10-20 | C64: 7 | D64: Apex Refining | E64: Webinar attended | F64: Webinar attended: qualified | G64: Qualified | H64: C1w | I64: Named in the file | J64: Kai Ong | K64: 8 | L64: 60 | M64: Not run
A65: G01 | B65: 2026-10-20 | C65: 8 | D65: Apex Refining | E65: Webinar registered | F65: Webinar registered: qualified | G65: Qualified | H65: C1w | I65: Named in the file | J65: Kai Ong | K65: 9 | L65: 30 | M65: Not run
A66: G01 | B66: 2026-10-20 | C66: 9 | D66: Apex Refining | E66: Content download | F66: Content download: qualified | G66: Qualified | H66: C1w | I66: Named in the file | J66: Kai Ong | K66: 10 | L66: 60 | M66: Not run
A67: G01 | B67: 2026-10-20 | C67: 10 | D67: Apex Refining | E67: Email clicked | F67: Email clicked: qualified | G67: Qualified | H67: C1x | I67: Named in the file | J67: Kai Ong | K67: 11 | L67: 30 | M67: Not run
A68: G01 | B68: 2026-10-20 | C68: 11 | D68: Apex Refining | E68: Newsletter sign-up | F68: Newsletter sign-up: rejected D1 (does not predict buying) | G68: Rejected | H68: D1 | I68: Doesn't predict buying the pilot product | J68: Kai Ong | K68: 4 | M68: Not run
A69: G02 | B69: 2026-10-20 | C69: 2 | D69: Apex Refining | E69: Webinar attended | F69: Exact name: matched | G69: Qualified | H69: C1w | I69: Named in the file | J69: Kai Ong | K69: 5 | L69: 60 | M69: Not run
A70: G02 | B70: 2026-10-20 | C70: 3 | D70: APEX REFINING | E70: Content download | F70: Capitals: matched | G70: Qualified | H70: C1w | I70: Named in the file | J70: Kai Ong | K70: 6 | L70: 60 | M70: Not run
A71: G02 | B71: 2026-10-20 | C71: 4 | D71: Apex Refining | E71: Email clicked | F71: Double space and trailing space: matched | G71: Qualified | H71: C1x | I71: Named in the file | J71: Kai Ong | K71: 7 | L71: 30 | M71: Not run
A72: G02 | B72: 2026-10-20 | C72: 5 | D72: Apex Refining Ltd | E72: Webinar registered | F72: "Ltd" added: not matched (D4): names must be written as in the list | G72: Rejected | H72: D4 | I72: Company is not in the target universe | M72: Not run
A73: G02 | B73: 2026-10-20 | C73: 6 | D73: Unknown Refining | E73: Inquiry or RFQ | F73: Company not in the list: rejected D4 | G73: Rejected | H73: D4 | I73: Company is not in the target universe | M73: Not run
A74: G02 | B74: 2026-10-20 | C74: 7 | D74: (blank) | E74: Inquiry or RFQ | F74: No company name: rejected D3 | G74: Rejected | H74: D3 | I74: No company name | M74: Not run
A75: G02 | B75: 2026-10-20 | C75: 8 | D75: Tidewater Refining | E75: Inquiry or RFQ | F75: Company in the list but excluded (Australia): qualified, then not used | G75: Not used | H75: Y2 | I75: Qualified, but the account is excluded (Outside the pilot region (Australia)) | J75: Hu Koh | K75: 5 | L75: 100 | M75: Not run
A76: G03 | B76: 2026-10-20 | C76: 2 | D76: Apex Refining | E76: Webinar attended | F76: Email exactly as in the list: matched | G76: Qualified | H76: C1w | I76: Named in the file | J76: Kai Ong | K76: 5 | L76: 60 | M76: Not run
A77: G03 | B77: 2026-10-20 | C77: 3 | D77: Apex Refining | E77: Content download | F77: Email in capitals: matched | G77: Qualified | H77: C1w | I77: Named in the file | J77: Kai Ong | K77: 6 | L77: 60 | M77: Not run
A78: G03 | B78: 2026-10-20 | C78: 4 | D78: Apex Refining | E78: Email clicked | F78: LinkedIn URL: matched | G78: Qualified | H78: C1x | I78: Named in the file | J78: Kai Ong | K78: 7 | L78: 30 | M78: Not run
A79: G03 | B79: 2026-10-20 | C79: 5 | D79: Apex Refining | E79: Webinar registered | F79: LinkedIn URL in another form: matched | G79: Qualified | H79: C1w | I79: Named in the file | J79: Kai Ong | K79: 8 | L79: 30 | M79: Not run
A80: G03 | B80: 2026-10-20 | C80: 6 | D80: Apex Refining | E80: Inquiry or RFQ | F80: Person not in the list: rejected D4, offered as a suggested new contact | G80: Rejected | H80: D4 | I80: Person new.person@apexrefining.example is not in the lead file for this account (sent back as a suggested new contact) | M80: Not run
A81: G03 | B81: 2026-10-20 | C81: 7 | D81: Bayfront Refining | E81: Inquiry or RFQ | F81: No person named: given to the primary-persona contact (Mia Tan), flagged as auto-assigned | G81: Qualified | H81: Y2 | I81: Auto-assigned to the primary-persona contact | J81: Mia Tan | K81: 5 | L81: 100 | M81: Not run
A82: G03 | B82: 2026-10-20 | C82: 8 | D82: Larkspur Refining | E82: Inquiry or RFQ | F82: No person named, no primary contact at the account: given to Bea Ang, flagged | G82: Qualified | H82: Y2 | I82: Auto-assigned (no primary-persona contact) | J82: Bea Ang | K82: 5 | L82: 100 | M82: Not run
A83: G03 | B83: 2026-10-20 | C83: 9 | D83: Rosewood Refining | E83: Inquiry or RFQ | F83: No person named, primary opted out: given to the secondary contact, not the opted-out one | G83: Qualified | H83: Y2 | I83: Auto-assigned (no primary-persona contact) | J83: Fia Ng | K83: 5 | L83: 100 | M83: Not run
A84: G04 | B84: 2026-10-20 | C84: 2 | D84: Apex Refining | E84: Webinar attended | F84: YYYY-MM-DD: qualified | G84: Qualified | H84: C1w | I84: Named in the file | J84: Kai Ong | K84: 5 | L84: 60 | M84: Not run
A85: G04 | B85: 2026-10-20 | C85: 3 | D85: Apex Refining | E85: Content download | F85: On the scoring date (0 days old): qualified | G85: Qualified | H85: C1w | I85: Named in the file | J85: Kai Ong | K85: 0 | L85: 60 | M85: Not run
A86: G04 | B86: 2026-10-20 | C86: 4 | D86: Apex Refining | E86: Email clicked | F86: Blank: rejected D3 | G86: Rejected | H86: D3 | I86: No event date | J86: Kai Ong | M86: Not run
A87: G04 | B87: 2026-10-20 | C87: 5 | D87: Apex Refining | E87: Webinar registered | F87: DD/MM/YYYY: rejected D3 | G87: Rejected | H87: D3 | I87: Event date "15/10/2026" isn't YYYY-MM-DD | J87: Kai Ong | M87: Not run
A88: G04 | B88: 2026-10-20 | C88: 6 | D88: Apex Refining | E88: Inquiry or RFQ | F88: YYYY/MM/DD: rejected D3 | G88: Rejected | H88: D3 | I88: Event date "2026/10/15" isn't YYYY-MM-DD | J88: Kai Ong | M88: Not run
A89: G04 | B89: 2026-10-20 | C89: 7 | D89: Apex Refining | E89: Leadership change | F89: Written in words: rejected D3 | G89: Rejected | H89: D3 | I89: Event date "Oct 15, 2026" isn't YYYY-MM-DD | J89: Kai Ong | M89: Not run
A90: G04 | B90: 2026-10-20 | C90: 8 | D90: Apex Refining | E90: Capital project | F90: 30 February: rejected D3 | G90: Rejected | H90: D3 | I90: Event date "2026-02-30" isn't YYYY-MM-DD | J90: Kai Ong | M90: Not run
A91: G04 | B91: 2026-10-20 | C91: 9 | D91: Apex Refining | E91: Service contract renewal | F91: After the scoring date: rejected D3 | G91: Rejected | H91: D3 | I91: Event date 2026-10-21 is after the scoring date 2026-10-20 | J91: Kai Ong | K91: -1 | M91: Not run
A92: G05 | B92: 2026-10-20 | C92: 2 | D92: Apex Refining | E92: Inquiry or RFQ | F92: Lower case: accepted | G92: Qualified | H92: Y2 | I92: Named in the file | J92: Kai Ong | K92: 5 | L92: 100 | M92: Not run
A93: G05 | B93: 2026-10-20 | C93: 3 | D93: Apex Refining | E93: Webinar attended | F93: Capitals: accepted | G93: Qualified | H93: C1w | I93: Named in the file | J93: Kai Ong | K93: 6 | L93: 60 | M93: Not run
A94: G05 | B94: 2026-10-20 | C94: 4 | D94: Apex Refining | E94: Webinar attend | F94: Misspelt: rejected D3 | G94: Rejected | H94: D3 | I94: Signal type "Webinar attend" isn't on the list | J94: Kai Ong | K94: 7 | M94: Not run
A95: G05 | B95: 2026-10-20 | C95: 5 | D95: Apex Refining | E95: Trade show visit | F95: Not on the list: rejected D3 | G95: Rejected | H95: D3 | I95: Signal type "Trade show visit" isn't on the list | J95: Kai Ong | K95: 8 | M95: Not run
A96: G05 | B96: 2026-10-20 | C96: 6 | D96: Apex Refining | E96: RFQ | F96: Short form "RFQ": rejected D3 | G96: Rejected | H96: D3 | I96: Signal type "RFQ" isn't on the list | J96: Kai Ong | K96: 9 | M96: Not run
A97: G05 | B97: 2026-10-20 | C97: 7 | D97: Apex Refining | E97: (blank) | F97: Blank: rejected D3 | G97: Rejected | H97: D3 | I97: Signal type "" isn't on the list | J97: Kai Ong | K97: 10 | M97: Not run
A98: G06 | B98: 2026-10-20 | C98: 2 | D98: Apex Refining | E98: Webinar attended | F98: First: qualified | G98: Qualified | H98: C1w | I98: Named in the file | J98: Kai Ong | K98: 10 | L98: 60 | M98: Not run
A99: G06 | B99: 2026-10-20 | C99: 3 | D99: Apex Refining | E99: Webinar attended | F99: Same person, type and date: rejected D5 | G99: Rejected | H99: D5 | I99: Same event already recorded (SIG-01) | J99: Kai Ong | K99: 10 | M99: Not run
A100: G06 | B100: 2026-10-20 | C100: 4 | D100: Apex Refining | E100: Webinar attended | F100: Same again, written differently: rejected D5 | G100: Rejected | H100: D5 | I100: Same event already recorded (SIG-01) | J100: Kai Ong | K100: 10 | M100: Not run
A101: G06 | B101: 2026-10-20 | C101: 5 | D101: Apex Refining | E101: Webinar attended | F101: Next day: a separate event, qualified | G101: Qualified | H101: C1w | I101: Named in the file | J101: Kai Ong | K101: 11 | L101: 60 | M101: Not run
A102: G06 | B102: 2026-10-20 | C102: 6 | D102: Apex Refining | E102: Webinar attended | F102: Same day, other person: qualified | G102: Qualified | H102: C1w | I102: Named in the file | J102: Lena Koh | K102: 10 | L102: 60 | M102: Not run
A103: G06 | B103: 2026-10-20 | C103: 7 | D103: Bayfront Refining | E103: Content download | F103: No person named: auto-assigned | G103: Qualified | H103: C1w | I103: Auto-assigned to the primary-persona contact | J103: Mia Tan | K103: 5 | L103: 60 | M103: Not run
A104: G06 | B104: 2026-10-20 | C104: 8 | D104: Bayfront Refining | E104: Content download | F104: Same row again: auto-assigned to the same person, rejected D5 | G104: Rejected | H104: D5 | I104: Same event already recorded (SIG-06) | J104: Mia Tan | K104: 5 | M104: Not run
A105: G07 | B105: 2026-10-20 | C105: 2 | D105: Apex Refining | E105: Inquiry or RFQ | F105: Inquiry or RFQ, 89 days: last day it counts, qualified with a small weight | G105: Qualified | H105: Y2 | I105: Named in the file | J105: Kai Ong | K105: 89 | L105: 1.7 | M105: Not run
A106: G07 | B106: 2026-10-20 | C106: 3 | D106: Bayfront Refining | E106: Inquiry or RFQ | F106: Inquiry or RFQ, 90 days: stale, rejected D2 | G106: Rejected | H106: D2 | I106: 90 days old; this signal type counts for 90 days | J106: Mia Tan | K106: 90 | M106: Not run
A107: G07 | B107: 2026-10-20 | C107: 4 | D107: Apex Refining | E107: Installed system near end of support | F107: Installed system near end of support, 729 days: last day it counts, qualified with a small weight | G107: Qualified | H107: Y1 | I107: Named in the file | J107: Kai Ong | K107: 729 | L107: 0.3 | M107: Not run
A108: G07 | B108: 2026-10-20 | C108: 5 | D108: Bayfront Refining | E108: Installed system near end of support | F108: Installed system near end of support, 730 days: stale, rejected D2 | G108: Rejected | H108: D2 | I108: 730 days old; this signal type counts for 730 days | J108: Mia Tan | K108: 730 | M108: Not run
A109: G07 | B109: 2026-10-20 | C109: 6 | D109: Apex Refining | E109: Service contract renewal | F109: Service contract renewal, 179 days: last day it counts, qualified with a small weight | G109: Qualified | H109: Y1 | I109: Named in the file | J109: Kai Ong | K109: 179 | L109: 0.7 | M109: Not run
...

Sheet Scoring accounts
A1: File | B1: Score as of | C1: Account | D1: Fit (0-100) | E1: Timing (0-100) | F1: Score (0-100) | G1: Tier | H1: Qualified signals | I1: Confidence, or why not scored
A2: S01 | B2: 2026-10-20 | C2: Apex Refining | D2: 100 | E2: 50 | F2: 50 | G2: A | H2: 1 | I2: medium
A3: S01 | B3: 2026-10-20 | C3: Bayfront Refining | D3: 100 | E3: 50 | F3: 50 | G3: A | H3: 1 | I3: medium
A4: S01 | B4: 2026-10-20 | C4: Coldwater Refining | D4: 100 | E4: 40 | F4: 40 | G4: A | H4: 1 | I4: medium
A5: S01 | B5: 2026-10-20 | C5: Driftwood Refining | D5: 100 | E5: 30 | F5: 30 | G5: B | H5: 1 | I5: medium
A6: S01 | B6: 2026-10-20 | C6: Moorland Refining | D6: 94 | E6: 30 | F6: 28.2 | G6: B | H6: 1 | I6: medium
A7: S01 | B7: 2026-10-20 | C7: Juniper Fuels | D7: 50 | E7: 50 | F7: 25 | G7: B | H7: 1 | I7: low
A8: S01 | B8: 2026-10-20 | C8: Newhaven Petrochem | D8: 75 | E8: 22.5 | F8: 16.9 | G8: C | H8: 1 | I8: medium
A9: S01 | B9: 2026-10-20 | C9: Eastgate Refining | D9: 100 | E9: 15 | F9: 15 | G9: C | H9: 1 | I9: medium
A10: S01 | B10: 2026-10-20 | C10: Fairhaven Refining | D10: 100 | E10: 0 | F10: 0 | G10: Watch list | H10: 0 | I10: medium
A11: S01 | B11: 2026-10-20 | C11: Stonegate Refining | D11: 100 | E11: 0 | F11: 0 | G11: Watch list | H11: 0 | I11: medium
A12: S01 | B12: 2026-10-20 | C12: Larkspur Refining | D12: 97 | E12: 0 | F12: 0 | G12: Watch list | H12: 0 | I12: low
A13: S01 | B13: 2026-10-20 | C13: Rosewood Refining | D13: 97 | E13: 0 | F13: 0 | G13: Watch list | H13: 0 | I13: low
... A16: S01 | B16: 2026-10-20 | C16: Oakridge Water | D16: 60 | E16: 0 | F16: 0 | G16: Watch list | H16: 0 | I16: medium
A17: S01 | B17: 2026-10-20 | C17: Kingsbridge Fuels | D17: 49 | G17: Below fit floor | H17: 0
A18: S01 | B18: 2026-10-20 | C18: Tidewater Refining | G18: Excluded | H18: 0 | I18: Outside the pilot region (Australia)
A19: S01 | B19: 2026-12-20 | C19: Bayfront Refining | D19: 100 | E19: 50 | F19: 50 | G19: A | H19: 1 | I19: medium
A20: S01 | B20: 2026-12-20 | C20: Coldwater Refining | D20: 100 | E20: 38.4 | F20: 38.4 | G20: A | H20: 1 | I20: medium
A21: S01 | B21: 2026-12-20 | C21: Moorland Refining | D21: 94 | E21: 29.7 | F21: 27.9 | G21: B | H21: 1 | I21: medium
A22: S01 | B22: 2026-12-20 | C22: Driftwood Refining | D22: 100 | E22: 21.8 | F22: 21.8 | G22: B | H22: 1 | I22: medium
A23: S01 | B23: 2026-12-20 | C23: Apex Refining | D23: 100 | E23: 20 | F23: 20 | G23: B | H23: 1 | I23: medium
A24: S01 | B24: 2026-12-20 | C24: Juniper Fuels | D24: 50 | E24: 20 | F24: 10 | G24: C | H24: 1 | I24: low
A25: S01 | B25: 2026-12-20 | C25: Newhaven Petrochem | D25: 75 | E25: 12.2 | F25: 9.2 | G25: C | H25: 1 | I25: medium
A26: S01 | B26: 2026-12-20 | C26: Eastgate Refining | D26: 100 | E26: 0 | F26: 0 | G26: Watch list | H26: 0 | I26: medium
A27: S01 | B27: 2026-12-20 | C27: Fairhaven Refining | D27: 100 | E27: 0 | F27: 0 | G27: Watch list | H27: 0 | I27: medium
A28: S01 | B28: 2026-12-20 | C28: Stonegate Refining | D28: 100 | E28: 0 | F28: 0 | G28: Watch list | H28: 0 | I28: medium
A29: S01 | B29: 2026-12-20 | C29: Larkspur Refining | D29: 97 | E29: 0 | F29: 0 | G29: Watch list | H29: 0 | I29: low
A30: S01 | B30: 2026-12-20 | C30: Rosewood Refining | D30: 97 | E30: 0 | F30: 0 | G30: Watch list | H30: 0 | I30: low
... A33: S01 | B33: 2026-12-20 | C33: Oakridge Water | D33: 60 | E33: 0 | F33: 0 | G33: Watch list | H33: 0 | I33: medium
A34: S01 | B34: 2026-12-20 | C34: Kingsbridge Fuels | D34: 49 | G34: Below fit floor | H34: 0
A35: S01 | B35: 2026-12-20 | C35: Tidewater Refining | G35: Excluded | H35: 0 | I35: Outside the pilot region (Australia)
A36: S01 | B36: 2027-04-20 | C36: Bayfront Refining | D36: 100 | E36: 50 | F36: 50 | G36: A | H36: 1 | I36: medium
A37: S01 | B37: 2027-04-20 | C37: Coldwater Refining | D37: 100 | E37: 20.8 | F37: 20.8 | G37: B | H37: 1 | I37: medium
A38: S01 | B38: 2027-04-20 | C38: Apex Refining | D38: 100 | E38: 0 | F38: 0 | G38: Watch list | H38: 0 | I38: medium
A39: S01 | B39: 2027-04-20 | C39: Driftwood Refining | D39: 100 | E39: 0 | F39: 0 | G39: Watch list | H39: 0 | I39: medium
A40: S01 | B40: 2027-04-20 | C40: Eastgate Refining | D40: 100 | E40: 0 | F40: 0 | G40: Watch list | H40: 0 | I40: medium
A41: S01 | B41: 2027-04-20 | C41: Fairhaven Refining | D41: 100 | E41: 0 | F41: 0 | G41: Watch list | H41: 0 | I41: medium
A42: S01 | B42: 2027-04-20 | C42: Stonegate Refining | D42: 100 | E42: 0 | F42: 0 | G42: Watch list | H42: 0 | I42: medium
A43: S01 | B43: 2027-04-20 | C43: Larkspur Refining | D43: 97 | E43: 0 | F43: 0 | G43: Watch list | H43: 0 | I43: low
A44: S01 | B44: 2027-04-20 | C44: Rosewood Refining | D44: 97 | E44: 0 | F44: 0 | G44: Watch list | H44: 0 | I44: low
A45: S01 | B45: 2027-04-20 | C45: Quarry Hill Engineering | D45: 96 | E45: 0 | F45: 0 | G45: Watch list | H45: 0 | I45: medium
A46: S01 | B46: 2027-04-20 | C46: Moorland Refining | D46: 94 | E46: 0 | F46: 0 | G46: Watch list | H46: 0 | I46: medium
A47: S01 | B47: 2027-04-20 | C47: Pebblebrook Refining | D47: 85 | E47: 0 | F47: 0 | G47: Watch list | H47: 0 | I47: medium
... A50: S01 | B50: 2027-04-20 | C50: Juniper Fuels | D50: 50 | E50: 0 | F50: 0 | G50: Watch list | H50: 0 | I50: low
A51: S01 | B51: 2027-04-20 | C51: Kingsbridge Fuels | D51: 49 | G51: Below fit floor | H51: 0
A52: S01 | B52: 2027-04-20 | C52: Tidewater Refining | G52: Excluded | H52: 0 | I52: Outside the pilot region (Australia)
A53: S02 | B53: 2026-10-20 | C53: Apex Refining | D53: 100 | E53: 50 | F53: 50 | G53: A | H53: 1 | I53: medium
A54: S02 | B54: 2026-10-20 | C54: Bayfront Refining | D54: 100 | E54: 35 | F54: 35 | G54: A | H54: 1 | I54: medium
A55: S02 | B55: 2026-10-20 | C55: Coldwater Refining | D55: 100 | E55: 34.2 | F55: 34.2 | G55: B | H55: 1 | I55: medium
A56: S02 | B56: 2026-10-20 | C56: Driftwood Refining | D56: 100 | E56: 20 | F56: 20 | G56: B | H56: 1 | I56: medium
A57: S02 | B57: 2026-10-20 | C57: Eastgate Refining | D57: 100 | E57: 19.2 | F57: 19.2 | G57: C | H57: 1 | I57: medium
A58: S02 | B58: 2026-10-20 | C58: Fairhaven Refining | D58: 100 | E58: 0 | F58: 0 | G58: Watch list | H58: 0 | I58: medium
A59: S02 | B59: 2026-10-20 | C59: Stonegate Refining | D59: 100 | E59: 0 | F59: 0 | G59: Watch list | H59: 0 | I59: medium
A60: S02 | B60: 2026-10-20 | C60: Larkspur Refining | D60: 97 | E60: 0 | F60: 0 | G60: Watch list | H60: 0 | I60: low
A61: S02 | B61: 2026-10-20 | C61: Rosewood Refining | D61: 97 | E61: 0 | F61: 0 | G61: Watch list | H61: 0 | I61: low
A62: S02 | B62: 2026-10-20 | C62: Quarry Hill Engineering | D62: 96 | E62: 0 | F62: 0 | G62: Watch list | H62: 0 | I62: medium
A63: S02 | B63: 2026-10-20 | C63: Moorland Refining | D63: 94 | E63: 0 | F63: 0 | G63: Watch list | H63: 0 | I63: medium
A64: S02 | B64: 2026-10-20 | C64: Pebblebrook Refining | D64: 85 | E64: 0 | F64: 0 | G64: Watch list | H64: 0 | I64: medium
... A67: S02 | B67: 2026-10-20 | C67: Juniper Fuels | D67: 50 | E67: 0 | F67: 0 | G67: Watch list | H67: 0 | I67: low
A68: S02 | B68: 2026-10-20 | C68: Kingsbridge Fuels | D68: 49 | G68: Below fit floor | H68: 0
A69: S02 | B69: 2026-10-20 | C69: Tidewater Refining | G69: Excluded | H69: 0 | I69: Outside the pilot region (Australia)
A70: S03 | B70: 2026-10-20 | C70: Apex Refining | D70: 100 | E70: 50 | F70: 50 | G70: A | H70: 1 | I70: medium
A71: S03 | B71: 2026-10-20 | C71: Larkspur Refining | D71: 97 | E71: 50 | F71: 48.5 | G71: A | H71: 1 | I71: low
A72: S03 | B72: 2026-10-20 | C72: Quarry Hill Engineering | D72: 96 | E72: 50 | F72: 48 | G72: A | H72: 1 | I72: medium
A73: S03 | B73: 2026-10-20 | C73: Moorland Refining | D73: 94 | E73: 50 | F73: 47 | G73: A | H73: 1 | I73: medium
A74: S03 | B74: 2026-10-20 | C74: Pebblebrook Refining | D74: 85 | E74: 50 | F74: 42.5 | G74: A | H74: 1 | I74: medium
A75: S03 | B75: 2026-10-20 | C75: Newhaven Petrochem | D75: 75 | E75: 50 | F75: 37.5 | G75: A | H75: 1 | I75: medium
A76: S03 | B76: 2026-10-20 | C76: Oakridge Water | D76: 60 | E76: 50 | F76: 30 | G76: B | H76: 1 | I76: medium
A77: S03 | B77: 2026-10-20 | C77: Juniper Fuels | D77: 50 | E77: 50 | F77: 25 | G77: B | H77: 1 | I77: low
A78: S03 | B78: 2026-10-20 | C78: Bayfront Refining | D78: 100 | E78: 0 | F78: 0 | G78: Watch list | H78: 0 | I78: medium
A79: S03 | B79: 2026-10-20 | C79: Coldwater Refining | D79: 100 | E79: 0 | F79: 0 | G79: Watch list | H79: 0 | I79: medium
A80: S03 | B80: 2026-10-20 | C80: Driftwood Refining | D80: 100 | E80: 0 | F80: 0 | G80: Watch list | H80: 0 | I80: medium
A81: S03 | B81: 2026-10-20 | C81: Eastgate Refining | D81: 100 | E81: 0 | F81: 0 | G81: Watch list | H81: 0 | I81: medium
... A84: S03 | B84: 2026-10-20 | C84: Rosewood Refining | D84: 97 | E84: 0 | F84: 0 | G84: Watch list | H84: 0 | I84: low
A85: S03 | B85: 2026-10-20 | C85: Kingsbridge Fuels | D85: 49 | G85: Below fit floor | H85: 0
A86: S03 | B86: 2026-10-20 | C86: Tidewater Refining | G86: Excluded | H86: 0 | I86: Outside the pilot region (Australia)
A87: S04 | B87: 2026-10-20 | C87: Apex Refining | D87: 100 | E87: 68.8 | F87: 68.8 | G87: A | H87: 3 | I87: high
A88: S04 | B88: 2026-10-20 | C88: Bayfront Refining | D88: 100 | E88: 65 | F88: 65 | G88: A | H88: 2 | I88: high
A89: S04 | B89: 2026-10-20 | C89: Coldwater Refining | D89: 100 | E89: 43 | F89: 43 | G89: A | H89: 2 | I89: high
A90: S04 | B90: 2026-10-20 | C90: Driftwood Refining | D90: 100 | E90: 0 | F90: 0 | G90: Watch list | H90: 0 | I90: medium
A91: S04 | B91: 2026-10-20 | C91: Eastgate Refining | D91: 100 | E91: 0 | F91: 0 | G91: Watch list | H91: 0 | I91: medium
A92: S04 | B92: 2026-10-20 | C92: Fairhaven Refining | D92: 100 | E92: 0 | F92: 0 | G92: Watch list | H92: 0 | I92: medium
A93: S04 | B93: 2026-10-20 | C93: Stonegate Refining | D93: 100 | E93: 0 | F93: 0 | G93: Watch list | H93: 0 | I93: medium
A94: S04 | B94: 2026-10-20 | C94: Larkspur Refining | D94: 97 | E94: 0 | F94: 0 | G94: Watch list | H94: 0 | I94: low
A95: S04 | B95: 2026-10-20 | C95: Rosewood Refining | D95: 97 | E95: 0 | F95: 0 | G95: Watch list | H95: 0 | I95: low
A96: S04 | B96: 2026-10-20 | C96: Quarry Hill Engineering | D96: 96 | E96: 0 | F96: 0 | G96: Watch list | H96: 0 | I96: medium
A97: S04 | B97: 2026-10-20 | C97: Moorland Refining | D97: 94 | E97: 0 | F97: 0 | G97: Watch list | H97: 0 | I97: medium
A98: S04 | B98: 2026-10-20 | C98: Pebblebrook Refining | D98: 85 | E98: 0 | F98: 0 | G98: Watch list | H98: 0 | I98: medium
... A101: S04 | B101: 2026-10-20 | C101: Juniper Fuels | D101: 50 | E101: 0 | F101: 0 | G101: Watch list | H101: 0 | I101: low
A102: S04 | B102: 2026-10-20 | C102: Kingsbridge Fuels | D102: 49 | G102: Below fit floor | H102: 0
A103: S04 | B103: 2026-10-20 | C103: Tidewater Refining | G103: Excluded | H103: 0 | I103: Outside the pilot region (Australia)
A104: S05 | B104: 2026-10-20 | C104: Apex Refining | D104: 100 | E104: 50 | F104: 50 | G104: A | H104: 1 | I104: medium
A105: S05 | B105: 2026-10-20 | C105: Bayfront Refining | D105: 100 | E105: 0 | F105: 0 | G105: Watch list | H105: 0 | I105: medium
A106: S05 | B106: 2026-10-20 | C106: Coldwater Refining | D106: 100 | E106: 0 | F106: 0 | G106: Watch list | H106: 0 | I106: medium
A107: S05 | B107: 2026-10-20 | C107: Driftwood Refining | D107: 100 | E107: 0 | F107: 0 | G107: Watch list | H107: 0 | I107: medium
A108: S05 | B108: 2026-10-20 | C108: Eastgate Refining | D108: 100 | E108: 0 | F108: 0 | G108: Watch list | H108: 0 | I108: medium
A109: S05 | B109: 2026-10-20 | C109: Fairhaven Refining | D109: 100 | E109: 0 | F109: 0 | G109: Watch list | H109: 0 | I109: medium
A110: S05 | B110: 2026-10-20 | C110: Larkspur Refining | D110: 97 | E110: 0 | F110: 0 | G110: Watch list | H110: 0 | I110: low
A111: S05 | B111: 2026-10-20 | C111: Rosewood Refining | D111: 97 | E111: 0 | F111: 0 | G111: Watch list | H111: 0 | I111: low
A112: S05 | B112: 2026-10-20 | C112: Moorland Refining | D112: 94 | E112: 0 | F112: 0 | G112: Watch list | H112: 0 | I112: medium
...

Sheet Summary
A1: Folder | B1: Files | C1: Not run | D1: Pass | E1: Fail | F1: Blocked | G1: Not in scope
A2: 1-Prospecting | B2: =COUNTIF(Files!$B:$B,A2) | C2: =COUNTIFS(Files!$B:$B,$A2,Files!$J:$J,"Not run") | D2: =COUNTIFS(Files!$B:$B,$A2,Files!$J:$J,"Pass") | E2: =COUNTIFS(Files!$B:$B,$A2,Files!$J:$J,"Fail") | F2: =COUNTIFS(Files!$B:$B,$A2,Files!$J:$J,"Blocked") | G2: =COUNTIFS(Files!$B:$B,$A2,Files!$J:$J,"Not in scope")
A3: 2-Account-Scoring | B3: =COUNTIF(Files!$B:$B,A3) | C3: =COUNTIFS(Files!$B:$B,$A3,Files!$J:$J,"Not run") | D3: =COUNTIFS(Files!$B:$B,$A3,Files!$J:$J,"Pass") | E3: =COUNTIFS(Files!$B:$B,$A3,Files!$J:$J,"Fail") | F3: =COUNTIFS(Files!$B:$B,$A3,Files!$J:$J,"Blocked") | G3: =COUNTIFS(Files!$B:$B,$A3,Files!$J:$J,"Not in scope")
A4: 3-Signal-rules | B4: =COUNTIF(Files!$B:$B,A4) | C4: =COUNTIFS(Files!$B:$B,$A4,Files!$J:$J,"Not run") | D4: =COUNTIFS(Files!$B:$B,$A4,Files!$J:$J,"Pass") | E4: =COUNTIFS(Files!$B:$B,$A4,Files!$J:$J,"Fail") | F4: =COUNTIFS(Files!$B:$B,$A4,Files!$J:$J,"Blocked") | G4: =COUNTIFS(Files!$B:$B,$A4,Files!$J:$J,"Not in scope")
A5: 4-Micro-segments-and-Review | B5: =COUNTIF(Files!$B:$B,A5) | C5: =COUNTIFS(Files!$B:$B,$A5,Files!$J:$J,"Not run") | D5: =COUNTIFS(Files!$B:$B,$A5,Files!$J:$J,"Pass") | E5: =COUNTIFS(Files!$B:$B,$A5,Files!$J:$J,"Fail") | F5: =COUNTIFS(Files!$B:$B,$A5,Files!$J:$J,"Blocked") | G5: =COUNTIFS(Files!$B:$B,$A5,Files!$J:$J,"Not in scope")
A6: Total | B6: =SUM(B2:B5) | C6: =SUM(C2:C5) | D6: =SUM(D2:D5) | E6: =SUM(E2:E5) | F6: =SUM(F2:F5) | G6: =SUM(G2:G5)
